protostrings.py
protostrings-1.0.0.dist-info/DESCRIPTION.rst
protostrings-1.0.0.dist-info/METADATA
protostrings-1.0.0.dist-info/RECORD
protostrings-1.0.0.dist-info/WHEEL
protostrings-1.0.0.dist-info/metadata.json
protostrings-1.0.0.dist-info/top_level.txt
