Metadata-Version: 2.0
Name: protostrings
Version: 1.0.0
Summary: String-like Objects
Home-page: https://github.com/orbisvicis/protostrings
Author: Yclept Nemo
Author-email: UNKNOWN
License: GPLv3
Platform: UNKNOWN
Classifier: Development Status :: 5 - Production/Stable
Classifier: Intended Audience :: Developers
Classifier: License :: OSI Approved :: GNU General Public License v3 or later (GPLv3+)
Classifier: Operating System :: OS Independent
Classifier: Programming Language :: Python :: 3 :: Only
Classifier: Topic :: Software Development :: Libraries
Requires-Python: >= 3
Requires-Dist: decorator
